[
    {
        "systemeNom": "DESKTOP-9JI9O3C",
        "systemeDate": "2025-03-07-23-08-24"
    },
    {
        "systemeNom": "DESKTOP-7KJ8J2T",
        "systemeDate": "2025-03-07-15-20-10"
    },
    {
        "systemeNom": "DESKTOP-XA83F4D",
        "systemeDate": "2025-03-07-18-45-00"
    },
    {
        "systemeNom": "LAPTOP-AD21H1K",
        "systemeDate": "2025-03-06-22-30-45"
    },
    {
        "systemeNom": "DESKTOP-KJ8L2H1",
        "systemeDate": "2025-03-08-01-05-10"
    },
    {
        "systemeNom": "LAPTOP-JM39J2L",
        "systemeDate": "2025-03-06-19-10-30"
    },
    {
        "systemeNom": "DESKTOP-4L5F4G6",
        "systemeDate": "2025-03-07-17-55-15"
    },
    {
        "systemeNom": "DESKTOP-Q2JK3F6",
        "systemeDate": "2025-03-05-11-15-00"
    },
    {
        "systemeNom": "DESKTOP-KJ42F1M",
        "systemeDate": "2025-03-07-21-00-45"
    },
    {
        "systemeNom": "LAPTOP-KH32J4F",
        "systemeDate": "2025-03-07-16-30-00"
    },
    {
        "systemeNom": "LAPTOP-3T4J8J5",
        "systemeDate": "2025-03-06-12-45-55"
    },
    {
        "systemeNom": "LAPTOP-HZ32J9K",
        "systemeDate": "2025-03-06-08-15-45"
    },
    {
        "systemeNom": "DESKTOP-K5Y3L7F",
        "systemeDate": "2025-03-07-23-05-00"
    },
    {
        "systemeNom": "DESKTOP-KL8F1T2",
        "systemeDate": "2025-03-05-19-40-10"
    },
    {
        "systemeNom": "DESKTOP-F6P2L4J",
        "systemeDate": "2025-03-07-20-30-20"
    },
    {
        "systemeNom": "LAPTOP-9H21T8K",
        "systemeDate": "2025-03-06-13-30-00"
    },
    {
        "systemeNom": "DESKTOP-PK19J7Q",
        "systemeDate": "2025-03-07-09-00-30"
    },
    {
        "systemeNom": "LAPTOP-YG9F3P1",
        "systemeDate": "2025-03-06-17-40-50"
    },
    {
        "systemeNom": "DESKTOP-TJ7L4F2",
        "systemeDate": "2025-03-07-18-10-35"
    },
    {
        "systemeNom": "LAPTOP-J9L8K2R",
        "systemeDate": "2025-03-07-22-15-25"
    },
    {
        "systemeNom": "DESKTOP-3P7F9Q8",
        "systemeDate": "2025-03-05-14-50-40"
    },
    {
        "systemeNom": "LAPTOP-V5L7J9Y",
        "systemeDate": "2025-03-07-23-30-30"
    },
    {
        "systemeNom": "DESKTOP-6H1L4F9",
        "systemeDate": "2025-03-07-14-20-35"
    },
    {
        "systemeNom": "LAPTOP-9J2K8M5",
        "systemeDate": "2025-03-07-10-30-10"
    },
    {
        "systemeNom": "DESKTOP-Q9M7N3B",
        "systemeDate": "2025-03-07-13-25-15"
    },
    {
        "systemeNom": "LAPTOP-3T4Y5G6",
        "systemeDate": "2025-03-06-07-15-45"
    },
    {
        "systemeNom": "DESKTOP-MF2L4K3",
        "systemeDate": "2025-03-06-14-45-10"
    },
    {
        "systemeNom": "LAPTOP-PJ6L4K2",
        "systemeDate": "2025-03-07-11-50-25"
    },
    {
        "systemeNom": "DESKTOP-GH8L4J7",
        "systemeDate": "2025-03-07-23-40-30"
    },
    {
        "systemeNom": "DESKTOP-KX2F9L5",
        "systemeDate": "2025-03-07-13-35-10"
    },
    {
        "systemeNom": "LAPTOP-LK3Y1F5",
        "systemeDate": "2025-03-06-12-00-00"
    },
    {
        "systemeNom": "DESKTOP-M9L2K4Y",
        "systemeDate": "2025-03-06-23-10-20"
    },
    {
        "systemeNom": "DESKTOP-N5K4L1T",
        "systemeDate": "2025-03-07-08-10-00"
    },
    {
        "systemeNom": "DESKTOP-TL2F9K7",
        "systemeDate": "2025-03-07-21-35-30"
    },
    {
        "systemeNom": "LAPTOP-XH7F5G9",
        "systemeDate": "2025-03-06-18-25-40"
    },
    {
        "systemeNom": "LAPTOP-3F1K4T5",
        "systemeDate": "2025-03-07-22-00-45"
    },
    {
        "systemeNom": "DESKTOP-RJ8K2Q7",
        "systemeDate": "2025-03-06-09-10-25"
    },
    {
        "systemeNom": "DESKTOP-4M9F5L8",
        "systemeDate": "2025-03-06-16-30-15"
    },
    {
        "systemeNom": "LAPTOP-N1K3Y6P",
        "systemeDate": "2025-03-07-20-10-55"
    },
    {
        "systemeNom": "DESKTOP-9T5K7J2",
        "systemeDate": "2025-03-07-16-05-50"
    },
    {
        "systemeNom": "LAPTOP-P6M4L1F",
        "systemeDate": "2025-03-07-14-40-20"
    },
    {
        "systemeNom": "DESKTOP-K6L2T1M",
        "systemeDate": "2025-03-07-15-05-00"
    },
    {
        "systemeNom": "LAPTOP-B7F3K2P",
        "systemeDate": "2025-03-06-21-20-45"
    },
    {
        "systemeNom": "DESKTOP-XK1L3F4",
        "systemeDate": "2025-03-07-09-45-10"
    },
    {
        "systemeNom": "LAPTOP-M1K7L3T",
        "systemeDate": "2025-03-06-10-35-25"
    },
    {
        "systemeNom": "DESKTOP-7J1K2L3",
        "systemeDate": "2025-03-06-18-00-50"
    },
    {
        "systemeNom": "LAPTOP-H7T3J5Q",
        "systemeDate": "2025-03-07-13-55-30"
    },
    {
        "systemeNom": "DESKTOP-B3F4K1L",
        "systemeDate": "2025-03-07-12-20-40"
    },
    {
        "systemeNom": "LAPTOP-6F9K2J8",
        "systemeDate": "2025-03-06-23-20-10"
    },
    {
        "systemeNom": "DESKTOP-8J3L2K4",
        "systemeDate": "2025-03-07-11-25-00"
    },
    {
        "systemeNom": "LAPTOP-P5J4L3F",
        "systemeDate": "2025-03-06-06-30-40"
    },
    {
        "systemeNom": "DESKTOP-Q1F4L2K",
        "systemeDate": "2025-03-07-17-20-35"
    }
]
